{"id":"ADDD97BB-6494-49C5-BC3A-EB7E595F9646","validationEntity":{"analysedDataType":"auto","dataResult":{}},"modelEntity":{"createdDate":"2021-06-08T13:00:35Z","id":"15397272-A0D4-4BC3-9319-92ADC196F56A","experimentID":"ADDD97BB-6494-49C5-BC3A-EB7E595F9646","title":"","modifiedDate":"2021-06-08T13:00:35Z","preferredFilename":"","version":"1.0","modelURL":"Models\/MyActivityClassifier%201.mlmodel"},"version":"1.0","settingEntity":{"augmentations":[],"suggestedColumns":["RecordID","SessionFrequency","SessionID","WatchAccX","WatchAccY","WatchAccZ","WatchGyroX","WatchGyroY","WatchGyroZ","WatchtImeIntervalSince1970"],"seedType":"default","transferLearningEmbeddingType":"dynamic","featureNames":["WatchAccX","WatchAccY","WatchAccZ","WatchGyroX","WatchGyroY","WatchGyroZ"],"algorithmType":"maxEnt","harVideoAugmentations":0,"taskType":"activityClassifier","suggestedColumnValues":["3, 3, 3, 3, 3…","60, 60, 60, 60, 60…","1, 1, 1, 1, 1…","0,34, 0,36, 0,39, 0,40, 0,41…","-0,55, -0,54, -0,51, -0,50, -0,48…","-0,72, -0,70, -0,66, -0,65, -0,61…","-0,37, -0,49, -0,59, -0,73, -0,89…","-0,03, -0,04, -0,05, -0,05, -0,05…","0,10, 0,12, 0,13, 0,15, 0,17…","1 623 161 201,68, 1 623 161 201,68, 1 623 161 201,70, 1 623 161 201,70, 1 623 161 201,72…"],"suggestedColumnTypes":["Int","Int","Int","Double","Double","Double","Double","Double","Double","Double"],"sampleRate":60,"styleTransferAlgorithmType":"image","predictionWindowSize":60,"iterationCount":30},"state":"trained","trainingEntity":{"finishTime":"2021-06-08T14:16:08Z","recipeTrainingResults":{"activityClassifier":{"confusionMatrix":[{"expected":"Slap","actual":"Slap","count":2475},{"expected":"Walking","actual":"Walking","count":2396}],"statsByLabel":{"Walking":{"count":2396,"precisionRecall":{"success":{"recall":1,"precision":1}}},"Slap":{"count":2475,"precisionRecall":{"success":{"recall":1,"precision":1}}}},"accuracy":1}},"dataResult":{"itemsCount":2,"columns":["RecordID","SessionFrequency","SessionID","WatchAccX","WatchAccY","WatchAccZ","WatchGyroX","WatchGyroY","WatchGyroZ","WatchtImeIntervalSince1970"],"dataURL":"file:\/\/\/Users\/ludovico\/Desktop\/Motion%20training\/","columnTypes":["Int","Int","Int","Double","Double","Double","Double","Double","Double","Double"],"classesCount":2,"dataSourceID":"5A8C1ACB-0AEB-4400-A11A-4CF6CF8E9294","analysis":{"summary":{"sampleCount":2,"classCount":2,"canUseValidation":0},"issues":[{"description":"2 classes found, including Walking, Slap","severity":"debug"},{"description":"Less than 100 total activity recording files found - add more to improve model validation","severity":"warning"},{"description":"Smallest class is \"Slap\" with 1 activity recording files","severity":"debug"},{"description":"Largest class is \"Walking\" with 1 activity recording files","severity":"debug"},{"description":"6 features are selected","severity":"good"}],"classifierAnalysis":{"columns":[],"vizualizerSpec":"","labelStats":{"Walking":1,"Slap":1}}},"columnValues":["3, 3, 3, 3, 3…","60, 60, 60, 60, 60…","1, 1, 1, 1, 1…","0,34, 0,36, 0,39, 0,40, 0,41…","-0,55, -0,54, -0,51, -0,50, -0,48…","-0,72, -0,70, -0,66, -0,65, -0,61…","-0,37, -0,49, -0,59, -0,73, -0,89…","-0,03, -0,04, -0,05, -0,05, -0,05…","0,10, 0,12, 0,13, 0,15, 0,17…","1 623 161 201,68, 1 623 161 201,68, 1 623 161 201,70, 1 623 161 201,70, 1 623 161 201,72…"]},"dataURL":"file:\/\/\/Users\/ludovico\/Desktop\/Motion%20training\/","featureExtractionCheckpointMayBeAvailable":false,"resumableCheckpointURL":"Checkpoints\/ADDD97BB-6494-49C5-BC3A-EB7E595F9646.MyActivityClassifier1.checkpoint","progress":[{"isLast":false,"currentRowIndex":0,"count":1,"tableDone":false,"acColumnHeader":{"hasValidation":false,"elapsedTime":8.6392790000000002,"trainingAccuracy":0.55430096387863159,"iterationCount":1,"validationAccuracy":0},"tableIndex":0,"percentComplete":0},{"isLast":false,"currentRowIndex":0,"count":2,"tableDone":false,"acColumnHeader":{"hasValidation":false,"elapsedTime":8.6749320000000001,"trainingAccuracy":0.64052557945251465,"iterationCount":2,"validationAccuracy":0},"tableIndex":0,"percentComplete":0},{"isLast":false,"currentRowIndex":0,"count":3,"tableDone":false,"acColumnHeader":{"hasValidation":false,"elapsedTime":8.6980570000000004,"trainingAccuracy":0.89919936656951904,"iterationCount":3,"validationAccuracy":0},"tableIndex":0,"percentComplete":0},{"isLast":false,"currentRowIndex":0,"count":4,"tableDone":false,"acColumnHeader":{"hasValidation":false,"elapsedTime":8.7197329999999997,"trainingAccuracy":0.89919936656951904,"iterationCount":4,"validationAccuracy":0},"tableIndex":0,"percentComplete":0},{"isLast":false,"currentRowIndex":0,"count":5,"tableDone":false,"acColumnHeader":{"hasValidation":false,"elapsedTime":8.7402029999999993,"trainingAccuracy":0.95996713638305664,"iterationCount":5,"validationAccuracy":0},"tableIndex":0,"percentComplete":0},{"isLast":false,"currentRowIndex":0,"count":6,"tableDone":false,"acColumnHeader":{"hasValidation":false,"elapsedTime":8.7647239999999993,"trainingAccuracy":0.9630466103553772,"iterationCount":6,"validationAccuracy":0},"tableIndex":0,"percentComplete":0},{"isLast":false,"currentRowIndex":0,"count":10,"tableDone":true,"acColumnHeader":{"hasValidation":false,"elapsedTime":8.8456279999999996,"trainingAccuracy":0.98768222332000732,"iterationCount":10,"validationAccuracy":0},"tableIndex":0,"percentComplete":0},{"isLast":false,"currentRowIndex":0,"count":11,"tableDone":false,"acColumnHeader":{"hasValidation":false,"elapsedTime":0.110263,"trainingAccuracy":1,"iterationCount":11,"validationAccuracy":0},"tableIndex":0,"percentComplete":0},{"isLast":false,"currentRowIndex":0,"count":12,"tableDone":false,"acColumnHeader":{"hasValidation":false,"elapsedTime":0.13297800000000001,"trainingAccuracy":1,"iterationCount":12,"validationAccuracy":0},"tableIndex":0,"percentComplete":0},{"isLast":false,"currentRowIndex":0,"count":13,"tableDone":false,"acColumnHeader":{"hasValidation":false,"elapsedTime":0.15290500000000001,"trainingAccuracy":1,"iterationCount":13,"validationAccuracy":0},"tableIndex":0,"percentComplete":0},{"isLast":false,"currentRowIndex":0,"count":14,"tableDone":false,"acColumnHeader":{"hasValidation":false,"elapsedTime":0.17249,"trainingAccuracy":0.98768222332000732,"iterationCount":14,"validationAccuracy":0},"tableIndex":0,"percentComplete":0},{"isLast":false,"currentRowIndex":0,"count":15,"tableDone":false,"acColumnHeader":{"hasValidation":false,"elapsedTime":0.19147700000000001,"trainingAccuracy":1,"iterationCount":15,"validationAccuracy":0},"tableIndex":0,"percentComplete":0},{"isLast":false,"currentRowIndex":0,"count":30,"tableDone":true,"acColumnHeader":{"hasValidation":false,"elapsedTime":0.61871399999999999,"trainingAccuracy":1,"iterationCount":30,"validationAccuracy":0},"tableIndex":0,"percentComplete":0}],"trainingAccuracy":1,"checkpointMetrics":{"20":{"metrics":{"loss":0.00030179502209648479,"accuracy":1},"createdDate":"2021-06-08T14:16:07Z","iteration":20},"30":{"metrics":{"loss":0.00078100082464516141,"accuracy":1},"createdDate":"2021-06-08T14:16:08Z","iteration":30},"10":{"metrics":{"loss":0.019217902794480324,"accuracy":0.98768222332000732},"createdDate":"2021-06-08T14:15:56Z","iteration":10}},"analysedDataType":"datasource","resumableCheckpoint":{"checkpointURL":"file:\/\/\/var\/folders\/vp\/4ww_gspx7mz1g5kr2fmb_hp00000gn\/T\/checkpoint.sessions\/ADDD97BB-6494-49C5-BC3A-EB7E595F9646\/ADDD97BB-6494-49C5-BC3A-EB7E595F9646.MyActivityClassifier1.checkpoint\/training-000000030.checkpoint","createdDate":"2021-06-08T14:16:08Z","iteration":30},"snapshottableCheckpoints":{"30":{"modelURL":"file:\/\/\/var\/folders\/vp\/4ww_gspx7mz1g5kr2fmb_hp00000gn\/T\/checkpoint.sessions\/ADDD97BB-6494-49C5-BC3A-EB7E595F9646\/ADDD97BB-6494-49C5-BC3A-EB7E595F9646.MyActivityClassifier1.checkpoint\/training-000000030.checkpoint.model\/checkpointModel.mlmodel","createdDate":"2021-06-08T14:16:08Z","iteration":30}},"dataSourceID":"5A8C1ACB-0AEB-4400-A11A-4CF6CF8E9294","snapshottableCheckpointModelURL":"Checkpoints\/ADDD97BB-6494-49C5-BC3A-EB7E595F9646.MyActivityClassifier1.checkpoint\/training-000000030.checkpoint.model\/checkpointModel.mlmodel","startTime":"2021-06-08T14:16:07Z"},"createdDate":"2021-06-08T13:00:35Z","snapshotRole":{"withSnapshots":["F9A4D70C-E4A4-4DAC-8D66-8D34F684D1F1"]},"evaluationEntities":[],"activityEntities":["experimentCreated",[{"id":"4364217D-2392-44AE-BCE4-9F0D11F43B96","title":"Model Source Created","createdDate":"2021-06-08T13:00:35Z","event":"experimentCreated","subtitle":"MyActivityClassifier 1"}],"trainingStarted",[{"id":"B9231FA3-8F68-4DDA-8C66-9FB71835BE40","title":"Training Started","createdDate":"2021-06-08T14:15:47Z","event":"trainingStarted","subtitle":"10 iterations"}],"trainingFinished",[{"id":"8E97CC3C-68B1-4000-A19F-A8C644E1E4DB","title":"Training Completed","createdDate":"2021-06-08T14:16:08Z","event":"trainingFinished","subtitle":"30 iterations"}],"trainingDataAdded",[{"id":"624B9A38-0BDA-48E5-B3CF-05F6BE119C51","title":"Training Data Added","createdDate":"2021-06-08T14:13:26Z","event":"trainingDataAdded","subtitle":"Motion training"}],"trainingExtended",[{"id":"DDEAA75F-41A8-4892-B464-140FB3AFFCC4","title":"Training Extended","createdDate":"2021-06-08T14:16:07Z","event":"trainingExtended","subtitle":"20 more iterations"}],"snapshotCreated",[{"id":"E6559EBC-0BEB-4F6B-981D-74B628C3E905","title":"Snapshot Saved","createdDate":"2021-06-08T14:16:06Z","event":"snapshotCreated","subtitle":"Snapshot created at iteration 10"}]],"title":"MyActivityClassifier 1","evaluationEntity":{"id":"cb5970fc-74d6-4246-82ae-ba94e0026a36","analysedDataType":"none","dataResult":{}},"evaluationState":"uninitialized","contentDataResult":{},"modifiedDate":"2021-06-08T14:32:05Z","preferredFilename":"MyActivityClassifier 1"}